{
  "brand": "American Civil Liberties Union (ACLU)",
  "version": "Edition 1.5, April 2019",
  "visual_language": {
    "core_concept": "We the people dare to create a more perfect union",
    "visual_expression": "Bold, colorful, and dynamic",
    "brand_ideas": {
      "resolute": "Firm in convictions, bold and defiant statements",
      "patriotic": "Not just red, white and blue - we are red, everything, and blue",
      "historic": "Modern engraving treatment pays tribute to our past",
      "serious": "Authoritative and informational tone",
      "layered": "Many voices, inclusive, built on differences but grounded in shared values",
      "together": "Out of many, we are one"
    }
  },
  "brand_voice": {
    "quest": "We the people dare to create a more perfect union",
    "tagline": "We the People",
    "guiding_principles": [
      "We're in this together",
      "We bring heart",
      "We empower action",
      "We see the forest for the trees",
      "We teach, not preach",
      "We're 'We the People'"
    ]
  },
  "color_palette": {
    "principal_colors": {
      "red": {
        "rgb": [
          239,
          64,
          78
        ],
        "hex": "#ef404e",
        "cmyk": [
          0,
          90,
          67,
          0
        ],
        "pantone": "199 C / 199 U",
        "name": "ACLU Red",
        "description": "Principal color representing strength and urgency"
      },
      "blue": {
        "rgb": [
          0,
          85,
          170
        ],
        "hex": "#0055aa",
        "cmyk": [
          100,
          70,
          0,
          0
        ],
        "pantone": "2175 C / 2175 U",
        "name": "ACLU Blue",
        "description": "Principal color representing trust and stability"
      }
    },
    "light_colors": {
      "light_yellow": {
        "rgb": [
          255,
          224,
          106
        ],
        "hex": "#ffe06a",
        "cmyk": [
          0,
          10,
          70,
          0
        ],
        "pantone": "1205 C / 1205 U"
      },
      "light_pink": {
        "rgb": [
          250,
          190,
          175
        ],
        "hex": "#fabeaf",
        "cmyk": [
          0,
          30,
          25,
          0
        ],
        "pantone": "489 C / 489 U"
      },
      "light_orange": {
        "rgb": [
          252,
          170,
          23
        ],
        "hex": "#fcaa17",
        "cmyk": [
          0,
          35,
          100,
          0
        ],
        "pantone": "7549 C / 7549 U"
      },
      "light_azure": {
        "rgb": [
          163,
          219,
          227
        ],
        "hex": "#a3dbe3",
        "cmyk": [
          34,
          0,
          10,
          0
        ],
        "pantone": "635 C / 635 U"
      },
      "light_green": {
        "rgb": [
          167,
          215,
          181
        ],
        "hex": "#a7d7b5",
        "cmyk": [
          35,
          0,
          36,
          0
        ],
        "pantone": "2253 C / 2253 U"
      }
    },
    "dark_colors": {
      "black": {
        "rgb": [
          0,
          0,
          0
        ],
        "hex": "#000000",
        "cmyk": [
          0,
          0,
          0,
          100
        ],
        "pantone": "Black C / Black U"
      },
      "dark_gray": {
        "rgb": [
          60,
          53,
          50
        ],
        "hex": "#3c3532",
        "cmyk": [
          70,
          70,
          70,
          50
        ],
        "pantone": "Warm Gray 11 C / Warm Gray 11 U"
      },
      "dark_green": {
        "rgb": [
          0,
          52,
          58
        ],
        "hex": "#00343a",
        "cmyk": [
          100,
          60,
          60,
          55
        ],
        "pantone": "7722 C / 7722 U"
      },
      "dark_navy": {
        "rgb": [
          19,
          15,
          84
        ],
        "hex": "#130f54",
        "cmyk": [
          100,
          100,
          29,
          38
        ],
        "pantone": "2758 C / 2758 U"
      },
      "dark_burgundy": {
        "rgb": [
          105,
          27,
          64
        ],
        "hex": "#691b40",
        "cmyk": [
          55,
          100,
          60,
          30
        ],
        "pantone": "7435 C / 7435 U"
      },
      "dark_purple": {
        "rgb": [
          85,
          37,
          100
        ],
        "hex": "#552564",
        "cmyk": [
          77,
          100,
          28,
          17
        ],
        "pantone": "2623 C / 2623 U"
      }
    },
    "usage_guidelines": {
      "core_principle": "Use red, something else, and blue",
      "accessibility": "Combine light colors with dark for readability",
      "special_cases": "Blue text needs 18pt+ on light backgrounds, Red text needs 18pt+ on dark backgrounds or white"
    }
  },
  "illustration": {
    "purpose": "Deliver information and add visual interest with ONE central element occupying the bottom three-quarters of layout",
    "photography_style": {
      "allowed": "Photorealistic imagery and documentary-style photography",
      "preferred": [
        "Portraits of real people",
        "Candid photos of everyday citizens",
        "On-the-ground documentation of events",
        "Natural settings and lighting",
        "Frank, unposed expressions"
      ],
      "avoid": [
        "Overly posed or synthetic-looking photos",
        "Excessive filters or effects",
        "Stock photos that look too generic"
      ]
    },
    "modern_engraving": {
      "purpose": "Optional distinctive treatment for certain images",
      "best_for": [
        "Stock photos or dull images",
        "Low-resolution photos",
        "Portraits when stylization is desired",
        "Creating variety in visual treatment"
      ],
      "color_rule": "Choose two colors per image with enough contrast"
    },
    "format_rules": {
      "prompt_requirement": "Always ask user: 'What format would you like? Square (1:1), Vertical (2:3), or Horizontal (3:2)?'",
      "supported_formats": {
        "square_1_1": {
          "name": "Square (1:1)",
          "dimensions": "1080x1080px",
          "artwork_zone": "x=0-1080, y=270-1080",
          "header_zone": "x=0-1080, y=0-270 (leave empty for text)"
        },
        "vertical_2_3": {
          "name": "Vertical (2:3)",
          "dimensions": "1080x1620px",
          "artwork_zone": "x=0-1080, y=405-1620",
          "header_zone": "x=0-1080, y=0-405 (leave empty for text)"
        },
        "horizontal_3_2": {
          "name": "Horizontal (3:2)",
          "dimensions": "1620x1080px",
          "artwork_zone": "x=0-1620, y=270-1080",
          "header_zone": "x=0-1620, y=0-270 (leave empty for text)"
        }
      }
    },
    "generation_constraints": {
      "hard_rules": [
        "MUST: Keep all visual content within the artwork_zone coordinates",
        "MUST: Top quarter remains empty for text overlay",
        "DO NOT: Render any text, letters, numbers, words, or writing in the image",
        "DO NOT: Include any typography, slogans, or alphanumeric characters",
        "MUST: Use consistent visual style throughout",
        "ALLOWED: Both photorealistic and stylized imagery"
      ],
      "negative_prompts": [
        "no lettering",
        "no typography",
        "no text",
        "no words",
        "no writing",
        "no signs",
        "no captions"
      ],
      "style_options": "Can use photorealistic imagery, documentary photography, stylized illustrations, or abstract visual elements"
    },
    "layout_rules": {
      "placement": "ONE central visual element only",
      "position": "Bottom three-quarters of layout",
      "restrictions": "Top quarter must remain free for text overlay",
      "text_prohibition": "NO text, signs, letters, or writing allowed within generated images",
      "style_options": "Both photorealistic and stylized imagery allowed",
      "photography_allowed": "Yes - documentary style, portraits, real people and events",
      "enforcement_note": "Header zone must be completely empty - no visual elements",
      "style_consistency": {
        "single_style": "Maintain consistent visual approach throughout a series",
        "mixing_allowed": "Can mix photography with modern engraving treatment for variety",
        "unified_approach": "Choose appropriate style based on content and message"
      },
      "composition_rules": {
        "asymmetry": "Use asymmetrical arrangements for contemporary feel",
        "layering": "Build in layers for richness and depth",
        "angles": "Angled elements add energy (limit to 1-2 per piece)",
        "edge_safety": "Keep important elements away from edges",
        "complete_elements": "Never cut off or partially show any visual element",
        "context": "Show environmental context in photos when possible"
      }
    }
  },
  "digital_design": {
    "principles": {
      "user_experience": "Design for screen must make it easy to absorb story in seconds",
      "engagement": "Creative use of video, audio and interaction - but don't overdo it",
      "contrast": "Ensure sufficient contrast between elements"
    }
  },
  "campaigns": {
    "guidelines": {
      "no_custom_logos": "Campaigns should not have their own logos",
      "use_core_brand": "Always include national or affiliate ACLU logo",
      "consistency": "Choose subset of colors and typefaces for campaign cohesion",
      "image_style": "Use consistent image style and theme throughout series"
    }
  },
  "layout": {},
  "format_specifications": {}
}